zhei/__init__.py
zhei/hello.py
zhei/models/__init__.py
zhei/models/lightning_model.py
zhei/utils/__init__.py
zhei/utils/catch_error.py
zhei/utils/eval_methods.py
zhei/utils/gpu.py
zhei/utils/io.py
zhei/utils/log.py
zhei/utils/notice.py
zhei/utils/result.py
zhei-0.0.3.dist-info/METADATA
zhei-0.0.3.dist-info/WHEEL
zhei-0.0.3.dist-info/top_level.txt
zhei-0.0.3.dist-info/RECORD
